Metadata-Version: 1.1
Name: micros
Version: 1.0.3
Summary: A skeleton command line program in Python.
Home-page: https://github.com/zwennesm/micros-cli
Author: Martijn Zwennes
Author-email: martijn.zwennes@debijenkorf.nl
License: Apache Licence 2.0
Keywords: cli
Platform: UNKNOWN
Classifier: Intended Audience :: Developers
